py_trashguard-0.1.3.dist-info/licenses/LICENSE
pytrashguard/__init__.py
pytrashguard/cli.py
pytrashguard/core.py
py_trashguard-0.1.3.dist-info/METADATA
py_trashguard-0.1.3.dist-info/WHEEL
py_trashguard-0.1.3.dist-info/entry_points.txt
py_trashguard-0.1.3.dist-info/top_level.txt
py_trashguard-0.1.3.dist-info/RECORD
