Metadata-Version: 2.4
Name: py-trashguard
Version: 0.1.3
Summary: Safe os.remove alternative with soft delete to .trash/ folder
Author-email: avishek devnath <avishekdevnath@gmail.com>
License-Expression: MIT
Classifier: Programming Language :: Python :: 3
Classifier: Operating System :: OS Independent
Classifier: Intended Audience :: Developers
Classifier: Topic :: Software Development :: Libraries :: Python Modules
Classifier: Topic :: System :: Filesystems
Requires-Python: >=3.7
License-File: LICENSE
Dynamic: license-file
